README.rst
setup.cfg
setup.py
Empty.egg-info/PKG-INFO
Empty.egg-info/SOURCES.txt
Empty.egg-info/dependency_links.txt
Empty.egg-info/not-zip-safe
Empty.egg-info/requires.txt
Empty.egg-info/top_level.txt
empty/__init__.py
empty/app.py
empty/commands.py
empty/exceptions.py
empty/filters.py
empty/logging.py