Metadata-Version: 1.1
Name: Empty
Version: 0.4.3
Summary: Wrapper which makes Flask development easier
Home-page: https://github.com/italomaia/empty
Author: Italo Maia
Author-email: italo.maia@gmail.com
License: BSD
Platform: any
Classifier: Environment :: Web Environment
Classifier: Intended Audience :: Developers
Classifier: License :: OSI Approved :: BSD License
Classifier: Operating System :: OS Independent
Classifier: Programming Language :: Python
Classifier: Programming Language :: Python :: 3.5
Classifier: Programming Language :: Python :: 3.6
Classifier: Topic :: Software Development :: Libraries :: Python Modules
